lakesoul/__init__.py
lakesoul/arrow/__init__.py
lakesoul/arrow/_lakesoul_dataset.cpython-39-x86_64-linux-gnu.so
lakesoul/arrow/_path_utils.py
lakesoul/arrow/dataset.py
lakesoul/huggingface/__init__.py
lakesoul/huggingface/from_lakesoul.py
lakesoul/metadata/__init__.py
lakesoul/metadata/dao.py
lakesoul/metadata/meta_ops.py
lakesoul/metadata/native_client.py
lakesoul/metadata/utils.py
lakesoul/metadata/generated/__init__.py
lakesoul/metadata/generated/entity_pb2.py
lakesoul/metadata/lib/__init__.py
lakesoul/metadata/lib/const.py
lakesoul/metadata/lib/lakesoul_metadata_c.py
lakesoul/metadata/lib/liblakesoul_metadata_c.so
lakesoul/ray/__init__.py
lakesoul/ray/read_lakesoul.py
lakesoul/spark/__init__.py
lakesoul/spark/tables.py
lakesoul/torch/__init__.py
lakesoul/torch/dataset.py
lakesoul.libs/liblakesoul_io_c-4e40fb78.so
lakesoul-1.0.2.dist-info/METADATA
lakesoul-1.0.2.dist-info/WHEEL
lakesoul-1.0.2.dist-info/top_level.txt
lakesoul-1.0.2.dist-info/RECORD
lakesoul-1.0.2.dist-info/licenses/LICENSE
