Metadata-Version: 2.4
Name: lakesoul
Version: 1.0.2
Summary: Python APIs for using LakeSoul
Author-email: LakeSoul Team <lakesoul-technical-discuss@lists.lfaidata.foundation>
License: Apache-2.0
Project-URL: Homepage, https://github.com/lakesoul-io/LakeSoul
Project-URL: Bug Tracker, https://github.com/lakesoul-io/LakeSoul/issues
Keywords: lakesoul,bigdata,ai
Classifier: Development Status :: 5 - Production/Stable
Classifier: Intended Audience :: Developers
Classifier: License :: OSI Approved :: Apache Software License
Classifier: Operating System :: OS Independent
Classifier: Topic :: Software Development :: Libraries :: Python Modules
Classifier: Programming Language :: Python :: 3
Requires-Python: >=3.8
License-File: LICENSE
Requires-Dist: pyarrow==16.1.0
Requires-Dist: numpy<2.0
Requires-Dist: protobuf>=5.0
Provides-Extra: torch
Requires-Dist: torch<2.5,>=1.11.0; extra == "torch"
Provides-Extra: pandas
Requires-Dist: pandas>=1.4; extra == "pandas"
Provides-Extra: datasets
Requires-Dist: datasets>=2.14; extra == "datasets"
Provides-Extra: ray
Requires-Dist: ray<2.11.0,>=2.7; extra == "ray"
Provides-Extra: pyspark
Requires-Dist: pyspark==3.3.1; extra == "pyspark"
Provides-Extra: all
Requires-Dist: torch<2.5,>=1.11; extra == "all"
Requires-Dist: pandas>=1.4; extra == "all"
Requires-Dist: datasets>=2.14; extra == "all"
Requires-Dist: ray<2.11.0,>=2.7; extra == "all"
Requires-Dist: pyspark==3.3.1; extra == "all"
Dynamic: license-file
